{"_path":"/post/20260703-turso-blackhole-timeout-abort-postmortem","_dir":"post","_draft":false,"_partial":false,"_locale":"","title":"timeout 不等於 abort：一個資料庫 black-hole 殺死我爬蟲三次的覆盤","description":"前情提要：我有一個 vibe coding 出來的台股行情爬蟲，跑在 Fly.io 上、資料庫用 Turso（libSQL，SQLite over HTTP）。上一篇〈讓 AI 全面 review 我 vibe code 出來的 production 專案〉提到，我做過一次全面 review、修掉 20 個問題。兩週後，它還是在盤中死掉了。","tags":"nodejs, turso, libsql, sqlite, abortcontroller, fetch, postmortem, 後端開發, 技術筆記","createdByAI":true,"customCreatedAt":"2026-07-03T04:02:00.000Z","readingTime":{"text":"9 min read","minutes":8.17,"time":490200,"words":1634},"body":{"type":"root","children":[{"type":"element","tag":"p","props":{},"children":[{"type":"text","value":"前情提要：我有一個 vibe coding 出來的台股行情爬蟲，跑在 Fly.io 上、資料庫用 Turso（libSQL，SQLite over HTTP）。上一篇〈讓 AI 全面 review 我 vibe code 出來的 production 專案〉提到，我做過一次全面 review、修掉 20 個問題。兩週後，它還是在盤中死掉了。"}]},{"type":"element","tag":"p","props":{},"children":[{"type":"text","value":"接下來十天內它一共死了三次，每次的死法都不一樣，每次的修復都揭開下一個洞。這篇覆盤想講的核心只有一句話："},{"type":"element","tag":"strong","props":{},"children":[{"type":"text","value":"timeout 不等於 abort"}]},{"type":"text","value":"——這五個字花了我兩次 production 事故才真正學會。"}]},{"type":"element","tag":"h2","props":{"id":"第一次凍死-12-小時"},"children":[{"type":"text","value":"第一次：凍死 12 小時"}]},{"type":"element","tag":"p","props":{},"children":[{"type":"text","value":"某天 11:01，爬蟲的 log 突然安靜。沒有錯誤、沒有 crash、process 活著、機器健康——就是不再有任何輸出。一路凍到晚上快午夜，我手動重開機器才復活。"}]},{"type":"element","tag":"p","props":{},"children":[{"type":"text","value":"事後診斷：Turso 的遠端連線出現了 black-hole——"},{"type":"element","tag":"strong","props":{},"children":[{"type":"text","value":"請求送出去，永遠沒有回應，也永遠不會 reject"}]},{"type":"text","value":"。而爬蟲的主體是一個單一的 async 迴圈："}]},{"type":"element","tag":"pre","props":{"code":"while (!shouldStop) {\n  const data = await fetchFromUpstream()\n  await db.batch(statements) // ← 這一行永遠不返回\n}\n","language":"ts","meta":"","className":"language-ts shiki shiki-themes one-dark-pro","style":""},"children":[{"type":"element","tag":"code","props":{"__ignoreMap":""},"children":[{"type":"element","tag":"span","props":{"class":"line","line":1},"children":[{"type":"element","tag":"span","props":{"style":"--shiki-default:#C678DD"},"children":[{"type":"text","value":"while"}]},{"type":"element","tag":"span","props":{"style":"--shiki-default:#ABB2BF"},"children":[{"type":"text","value":" ("}]},{"type":"element","tag":"span","props":{"style":"--shiki-default:#56B6C2"},"children":[{"type":"text","value":"!"}]},{"type":"element","tag":"span","props":{"style":"--shiki-default:#E06C75"},"children":[{"type":"text","value":"shouldStop"}]},{"type":"element","tag":"span","props":{"style":"--shiki-default:#ABB2BF"},"children":[{"type":"text","value":") {\n"}]}]},{"type":"element","tag":"span","props":{"class":"line","line":2},"children":[{"type":"element","tag":"span","props":{"style":"--shiki-default:#C678DD"},"children":[{"type":"text","value":"  const"}]},{"type":"element","tag":"span","props":{"style":"--shiki-default:#E5C07B"},"children":[{"type":"text","value":" data"}]},{"type":"element","tag":"span","props":{"style":"--shiki-default:#56B6C2"},"children":[{"type":"text","value":" ="}]},{"type":"element","tag":"span","props":{"style":"--shiki-default:#C678DD"},"children":[{"type":"text","value":" await"}]},{"type":"element","tag":"span","props":{"style":"--shiki-default:#61AFEF"},"children":[{"type":"text","value":" fetchFromUpstream"}]},{"type":"element","tag":"span","props":{"style":"--shiki-default:#ABB2BF"},"children":[{"type":"text","value":"()\n"}]}]},{"type":"element","tag":"span","props":{"class":"line","line":3},"children":[{"type":"element","tag":"span","props":{"style":"--shiki-default:#C678DD"},"children":[{"type":"text","value":"  await"}]},{"type":"element","tag":"span","props":{"style":"--shiki-default:#E5C07B"},"children":[{"type":"text","value":" db"}]},{"type":"element","tag":"span","props":{"style":"--shiki-default:#ABB2BF"},"children":[{"type":"text","value":"."}]},{"type":"element","tag":"span","props":{"style":"--shiki-default:#61AFEF"},"children":[{"type":"text","value":"batch"}]},{"type":"element","tag":"span","props":{"style":"--shiki-default:#ABB2BF"},"children":[{"type":"text","value":"("}]},{"type":"element","tag":"span","props":{"style":"--shiki-default:#E06C75"},"children":[{"type":"text","value":"statements"}]},{"type":"element","tag":"span","props":{"style":"--shiki-default:#ABB2BF"},"children":[{"type":"text","value":") "}]},{"type":"element","tag":"span","props":{"style":"--shiki-default:#7F848E;--shiki-default-font-style:italic"},"children":[{"type":"text","value":"// ← 這一行永遠不返回\n"}]}]},{"type":"element","tag":"span","props":{"class":"line","line":4},"children":[{"type":"element","tag":"span","props":{"style":"--shiki-default:#ABB2BF"},"children":[{"type":"text","value":"}\n"}]}]}]}]},{"type":"element","tag":"p","props":{},"children":[{"type":"text","value":"一個永遠不 settle 的 await，就把整條迴圈扣為人質。更糟的是第二層：「停止」的實作只是把 "},{"type":"element","tag":"code","props":{"className":[]},"children":[{"type":"text","value":"shouldStop"}]},{"type":"text","value":" 旗標設成 "},{"type":"element","tag":"code","props":{"className":[]},"children":[{"type":"text","value":"true"}]},{"type":"text","value":"，等迴圈下一輪去檢查——"},{"type":"element","tag":"strong","props":{},"children":[{"type":"text","value":"迴圈凍死了，就永遠沒有下一輪"}]},{"type":"text","value":"。按了三次停止 API 全部無效，背景的重連機制和 keep-alive 還在忠實地撐著這具屍體，不讓機器休眠。"}]},{"type":"element","tag":"p","props":{},"children":[{"type":"text","value":"修復有兩件事。一是給每個 DB 操作包上 timeout（當時用 "},{"type":"element","tag":"code","props":{"className":[]},"children":[{"type":"text","value":"Promise.race"}]},{"type":"text","value":"）；二是讓停止指令"},{"type":"element","tag":"strong","props":{},"children":[{"type":"text","value":"直接拆除背景資源"}]},{"type":"text","value":"（斷開監聽、清掉 keep-alive timer），不再等迴圈自己醒來。"}]},{"type":"element","tag":"pre","props":{"code":"export function stopCrawler() {\n  state.shouldStop = true\n  stopSideEffects() // 不等迴圈 return，直接拆\n}\n","language":"ts","meta":"","className":"language-ts shiki shiki-themes one-dark-pro","style":""},"children":[{"type":"element","tag":"code","props":{"__ignoreMap":""},"children":[{"type":"element","tag":"span","props":{"class":"line","line":1},"children":[{"type":"element","tag":"span","props":{"style":"--shiki-default:#C678DD"},"children":[{"type":"text","value":"export"}]},{"type":"element","tag":"span","props":{"style":"--shiki-default:#C678DD"},"children":[{"type":"text","value":" function"}]},{"type":"element","tag":"span","props":{"style":"--shiki-default:#61AFEF"},"children":[{"type":"text","value":" stopCrawler"}]},{"type":"element","tag":"span","props":{"style":"--shiki-default:#ABB2BF"},"children":[{"type":"text","value":"() {\n"}]}]},{"type":"element","tag":"span","props":{"class":"line","line":2},"children":[{"type":"element","tag":"span","props":{"style":"--shiki-default:#E5C07B"},"children":[{"type":"text","value":"  state"}]},{"type":"element","tag":"span","props":{"style":"--shiki-default:#ABB2BF"},"children":[{"type":"text","value":"."}]},{"type":"element","tag":"span","props":{"style":"--shiki-default:#E06C75"},"children":[{"type":"text","value":"shouldStop"}]},{"type":"element","tag":"span","props":{"style":"--shiki-default:#56B6C2"},"children":[{"type":"text","value":" ="}]},{"type":"element","tag":"span","props":{"style":"--shiki-default:#D19A66"},"children":[{"type":"text","value":" true\n"}]}]},{"type":"element","tag":"span","props":{"class":"line","line":3},"children":[{"type":"element","tag":"span","props":{"style":"--shiki-default:#61AFEF"},"children":[{"type":"text","value":"  stopSideEffects"}]},{"type":"element","tag":"span","props":{"style":"--shiki-default:#ABB2BF"},"children":[{"type":"text","value":"() "}]},{"type":"element","tag":"span","props":{"style":"--shiki-default:#7F848E;--shiki-default-font-style:italic"},"children":[{"type":"text","value":"// 不等迴圈 return，直接拆\n"}]}]},{"type":"element","tag":"span","props":{"class":"line","line":4},"children":[{"type":"element","tag":"span","props":{"style":"--shiki-default:#ABB2BF"},"children":[{"type":"text","value":"}\n"}]}]}]}]},{"type":"element","tag":"h2","props":{"id":"第二次oom"},"children":[{"type":"text","value":"第二次：OOM"}]},{"type":"element","tag":"p","props":{},"children":[{"type":"text","value":"修完之後我以為結束了。隔天開盤，Turso 又開始 black-hole——這次 timeout 如期觸發、迴圈如期 catch、如期重試。然後機器在三分鐘後 "},{"type":"element","tag":"strong","props":{},"children":[{"type":"text","value":"OOM 被系統擊殺"}]},{"type":"text","value":"。"}]},{"type":"element","tag":"p","props":{},"children":[{"type":"text","value":"原因是 "},{"type":"element","tag":"code","props":{"className":[]},"children":[{"type":"text","value":"Promise.race"}]},{"type":"text","value":" 的語義：它只是「不再等」輸掉的那個 promise，"},{"type":"element","tag":"strong","props":{},"children":[{"type":"text","value":"並沒有取消底層的操作"}]},{"type":"element","tag":"sup","props":{},"children":[{"type":"element","tag":"a","props":{"href":"#user-content-fn-1","ariaDescribedBy":["footnote-label"],"dataFootnoteRef":"","id":"user-content-fnref-1"},"children":[{"type":"text","value":"1"}]}]},{"type":"text","value":"。每次 timeout，那個卡死的 HTTP 請求仍然被 socket 釣著——連同已經序列化好的數 MB batch payload——GC 收不掉。迴圈每次重試又建立一個新的卡死請求。卡死的請求一個一個累積，heap 三分鐘撞頂。"}]},{"type":"element","tag":"p","props":{},"children":[{"type":"text","value":"這就是「timeout 不等於 abort」的第一課："},{"type":"element","tag":"strong","props":{},"children":[{"type":"text","value":"不等 ≠ 中止"}]},{"type":"text","value":"。你以為你放手了，其實資源還抓在手上。"}]},{"type":"element","tag":"p","props":{},"children":[{"type":"text","value":"正確的修法要下沉一層。Turso 的協議是 SQLite over HTTP，每個 DB 操作就是一個 HTTPS POST，而 client 允許注入自訂的 "},{"type":"element","tag":"code","props":{"className":[]},"children":[{"type":"text","value":"fetch"}]},{"type":"text","value":"。所以把 timeout 做在 fetch 層，用 "},{"type":"element","tag":"code","props":{"className":[]},"children":[{"type":"text","value":"AbortController"}]},{"type":"text","value":" 真正拆掉 socket"},{"type":"element","tag":"sup","props":{},"children":[{"type":"element","tag":"a","props":{"href":"#user-content-fn-2","ariaDescribedBy":["footnote-label"],"dataFootnoteRef":"","id":"user-content-fnref-2"},"children":[{"type":"text","value":"2"}]}]},{"type":"text","value":"："}]},{"type":"element","tag":"pre","props":{"code":"const timeoutFetch: typeof fetch = async (input, init) => {\n  const controller = new AbortController()\n  const timer = setTimeout(() => {\n    db = null // 丟掉 client，下次重建\n    controller.abort(new Error(`DB request timed out after ${TIMEOUT}ms`))\n  }, TIMEOUT)\n  try {\n    return await fetch(input, { ...init, signal: controller.signal })\n  }\n  finally {\n    clearTimeout(timer)\n  }\n}\n\nconst db = createClient({ url, authToken, fetch: timeoutFetch })\n","language":"ts","meta":"","className":"language-ts shiki shiki-themes one-dark-pro","style":""},"children":[{"type":"element","tag":"code","props":{"__ignoreMap":""},"children":[{"type":"element","tag":"span","props":{"class":"line","line":1},"children":[{"type":"element","tag":"span","props":{"style":"--shiki-default:#C678DD"},"children":[{"type":"text","value":"const"}]},{"type":"element","tag":"span","props":{"style":"--shiki-default:#61AFEF"},"children":[{"type":"text","value":" timeoutFetch"}]},{"type":"element","tag":"span","props":{"style":"--shiki-default:#ABB2BF"},"children":[{"type":"text","value":": "}]},{"type":"element","tag":"span","props":{"style":"--shiki-default:#C678DD"},"children":[{"type":"text","value":"typeof"}]},{"type":"element","tag":"span","props":{"style":"--shiki-default:#61AFEF"},"children":[{"type":"text","value":" fetch"}]},{"type":"element","tag":"span","props":{"style":"--shiki-default:#56B6C2"},"children":[{"type":"text","value":" ="}]},{"type":"element","tag":"span","props":{"style":"--shiki-default:#C678DD"},"children":[{"type":"text","value":" async"}]},{"type":"element","tag":"span","props":{"style":"--shiki-default:#ABB2BF"},"children":[{"type":"text","value":" ("}]},{"type":"element","tag":"span","props":{"style":"--shiki-default:#E06C75;--shiki-default-font-style:italic"},"children":[{"type":"text","value":"input"}]},{"type":"element","tag":"span","props":{"style":"--shiki-default:#ABB2BF"},"children":[{"type":"text","value":", "}]},{"type":"element","tag":"span","props":{"style":"--shiki-default:#E06C75;--shiki-default-font-style:italic"},"children":[{"type":"text","value":"init"}]},{"type":"element","tag":"span","props":{"style":"--shiki-default:#ABB2BF"},"children":[{"type":"text","value":") "}]},{"type":"element","tag":"span","props":{"style":"--shiki-default:#C678DD"},"children":[{"type":"text","value":"=>"}]},{"type":"element","tag":"span","props":{"style":"--shiki-default:#ABB2BF"},"children":[{"type":"text","value":" {\n"}]}]},{"type":"element","tag":"span","props":{"class":"line","line":2},"children":[{"type":"element","tag":"span","props":{"style":"--shiki-default:#C678DD"},"children":[{"type":"text","value":"  const"}]},{"type":"element","tag":"span","props":{"style":"--shiki-default:#E5C07B"},"children":[{"type":"text","value":" controller"}]},{"type":"element","tag":"span","props":{"style":"--shiki-default:#56B6C2"},"children":[{"type":"text","value":" ="}]},{"type":"element","tag":"span","props":{"style":"--shiki-default:#C678DD"},"children":[{"type":"text","value":" new"}]},{"type":"element","tag":"span","props":{"style":"--shiki-default:#61AFEF"},"children":[{"type":"text","value":" AbortController"}]},{"type":"element","tag":"span","props":{"style":"--shiki-default:#ABB2BF"},"children":[{"type":"text","value":"()\n"}]}]},{"type":"element","tag":"span","props":{"class":"line","line":3},"children":[{"type":"element","tag":"span","props":{"style":"--shiki-default:#C678DD"},"children":[{"type":"text","value":"  const"}]},{"type":"element","tag":"span","props":{"style":"--shiki-default:#E5C07B"},"children":[{"type":"text","value":" timer"}]},{"type":"element","tag":"span","props":{"style":"--shiki-default:#56B6C2"},"children":[{"type":"text","value":" ="}]},{"type":"element","tag":"span","props":{"style":"--shiki-default:#61AFEF"},"children":[{"type":"text","value":" setTimeout"}]},{"type":"element","tag":"span","props":{"style":"--shiki-default:#ABB2BF"},"children":[{"type":"text","value":"(() "}]},{"type":"element","tag":"span","props":{"style":"--shiki-default:#C678DD"},"children":[{"type":"text","value":"=>"}]},{"type":"element","tag":"span","props":{"style":"--shiki-default:#ABB2BF"},"children":[{"type":"text","value":" {\n"}]}]},{"type":"element","tag":"span","props":{"class":"line","line":4},"children":[{"type":"element","tag":"span","props":{"style":"--shiki-default:#E06C75"},"children":[{"type":"text","value":"    db"}]},{"type":"element","tag":"span","props":{"style":"--shiki-default:#56B6C2"},"children":[{"type":"text","value":" ="}]},{"type":"element","tag":"span","props":{"style":"--shiki-default:#D19A66"},"children":[{"type":"text","value":" null"}]},{"type":"element","tag":"span","props":{"style":"--shiki-default:#7F848E;--shiki-default-font-style:italic"},"children":[{"type":"text","value":" // 丟掉 client，下次重建\n"}]}]},{"type":"element","tag":"span","props":{"class":"line","line":5},"children":[{"type":"element","tag":"span","props":{"style":"--shiki-default:#E5C07B"},"children":[{"type":"text","value":"    controller"}]},{"type":"element","tag":"span","props":{"style":"--shiki-default:#ABB2BF"},"children":[{"type":"text","value":"."}]},{"type":"element","tag":"span","props":{"style":"--shiki-default:#61AFEF"},"children":[{"type":"text","value":"abort"}]},{"type":"element","tag":"span","props":{"style":"--shiki-default:#ABB2BF"},"children":[{"type":"text","value":"("}]},{"type":"element","tag":"span","props":{"style":"--shiki-default:#C678DD"},"children":[{"type":"text","value":"new"}]},{"type":"element","tag":"span","props":{"style":"--shiki-default:#61AFEF"},"children":[{"type":"text","value":" Error"}]},{"type":"element","tag":"span","props":{"style":"--shiki-default:#ABB2BF"},"children":[{"type":"text","value":"("}]},{"type":"element","tag":"span","props":{"style":"--shiki-default:#98C379"},"children":[{"type":"text","value":"`DB request timed out after "}]},{"type":"element","tag":"span","props":{"style":"--shiki-default:#C678DD"},"children":[{"type":"text","value":"${"}]},{"type":"element","tag":"span","props":{"style":"--shiki-default:#E5C07B"},"children":[{"type":"text","value":"TIMEOUT"}]},{"type":"element","tag":"span","props":{"style":"--shiki-default:#C678DD"},"children":[{"type":"text","value":"}"}]},{"type":"element","tag":"span","props":{"style":"--shiki-default:#98C379"},"children":[{"type":"text","value":"ms`"}]},{"type":"element","tag":"span","props":{"style":"--shiki-default:#ABB2BF"},"children":[{"type":"text","value":"))\n"}]}]},{"type":"element","tag":"span","props":{"class":"line","line":6},"children":[{"type":"element","tag":"span","props":{"style":"--shiki-default:#ABB2BF"},"children":[{"type":"text","value":"  }, "}]},{"type":"element","tag":"span","props":{"style":"--shiki-default:#E5C07B"},"children":[{"type":"text","value":"TIMEOUT"}]},{"type":"element","tag":"span","props":{"style":"--shiki-default:#ABB2BF"},"children":[{"type":"text","value":")\n"}]}]},{"type":"element","tag":"span","props":{"class":"line","line":7},"children":[{"type":"element","tag":"span","props":{"style":"--shiki-default:#C678DD"},"children":[{"type":"text","value":"  try"}]},{"type":"element","tag":"span","props":{"style":"--shiki-default:#ABB2BF"},"children":[{"type":"text","value":" {\n"}]}]},{"type":"element","tag":"span","props":{"class":"line","line":8},"children":[{"type":"element","tag":"span","props":{"style":"--shiki-default:#C678DD"},"children":[{"type":"text","value":"    return"}]},{"type":"element","tag":"span","props":{"style":"--shiki-default:#C678DD"},"children":[{"type":"text","value":" await"}]},{"type":"element","tag":"span","props":{"style":"--shiki-default:#61AFEF"},"children":[{"type":"text","value":" fetch"}]},{"type":"element","tag":"span","props":{"style":"--shiki-default:#ABB2BF"},"children":[{"type":"text","value":"("}]},{"type":"element","tag":"span","props":{"style":"--shiki-default:#E06C75"},"children":[{"type":"text","value":"input"}]},{"type":"element","tag":"span","props":{"style":"--shiki-default:#ABB2BF"},"children":[{"type":"text","value":", { ..."}]},{"type":"element","tag":"span","props":{"style":"--shiki-default:#E06C75"},"children":[{"type":"text","value":"init"}]},{"type":"element","tag":"span","props":{"style":"--shiki-default:#ABB2BF"},"children":[{"type":"text","value":", "}]},{"type":"element","tag":"span","props":{"style":"--shiki-default:#E06C75"},"children":[{"type":"text","value":"signal"}]},{"type":"element","tag":"span","props":{"style":"--shiki-default:#ABB2BF"},"children":[{"type":"text","value":": "}]},{"type":"element","tag":"span","props":{"style":"--shiki-default:#E5C07B"},"children":[{"type":"text","value":"controller"}]},{"type":"element","tag":"span","props":{"style":"--shiki-default:#ABB2BF"},"children":[{"type":"text","value":"."}]},{"type":"element","tag":"span","props":{"style":"--shiki-default:#E06C75"},"children":[{"type":"text","value":"signal"}]},{"type":"element","tag":"span","props":{"style":"--shiki-default:#ABB2BF"},"children":[{"type":"text","value":" })\n"}]}]},{"type":"element","tag":"span","props":{"class":"line","line":9},"children":[{"type":"element","tag":"span","props":{"style":"--shiki-default:#ABB2BF"},"children":[{"type":"text","value":"  }\n"}]}]},{"type":"element","tag":"span","props":{"class":"line","line":10},"children":[{"type":"element","tag":"span","props":{"style":"--shiki-default:#C678DD"},"children":[{"type":"text","value":"  finally"}]},{"type":"element","tag":"span","props":{"style":"--shiki-default:#ABB2BF"},"children":[{"type":"text","value":" {\n"}]}]},{"type":"element","tag":"span","props":{"class":"line","line":11},"children":[{"type":"element","tag":"span","props":{"style":"--shiki-default:#61AFEF"},"children":[{"type":"text","value":"    clearTimeout"}]},{"type":"element","tag":"span","props":{"style":"--shiki-default:#ABB2BF"},"children":[{"type":"text","value":"("}]},{"type":"element","tag":"span","props":{"style":"--shiki-default:#E06C75"},"children":[{"type":"text","value":"timer"}]},{"type":"element","tag":"span","props":{"style":"--shiki-default:#ABB2BF"},"children":[{"type":"text","value":")\n"}]}]},{"type":"element","tag":"span","props":{"class":"line","line":12},"children":[{"type":"element","tag":"span","props":{"style":"--shiki-default:#ABB2BF"},"children":[{"type":"text","value":"  }\n"}]}]},{"type":"element","tag":"span","props":{"class":"line","line":13},"children":[{"type":"element","tag":"span","props":{"style":"--shiki-default:#ABB2BF"},"children":[{"type":"text","value":"}\n"}]}]},{"type":"element","tag":"span","props":{"class":"line","line":14},"children":[{"type":"element","tag":"span","props":{"emptyLinePlaceholder":true},"children":[{"type":"text","value":"\n"}]}]},{"type":"element","tag":"span","props":{"class":"line","line":15},"children":[{"type":"element","tag":"span","props":{"style":"--shiki-default:#C678DD"},"children":[{"type":"text","value":"const"}]},{"type":"element","tag":"span","props":{"style":"--shiki-default:#E5C07B"},"children":[{"type":"text","value":" db"}]},{"type":"element","tag":"span","props":{"style":"--shiki-default:#56B6C2"},"children":[{"type":"text","value":" ="}]},{"type":"element","tag":"span","props":{"style":"--shiki-default:#61AFEF"},"children":[{"type":"text","value":" createClient"}]},{"type":"element","tag":"span","props":{"style":"--shiki-default:#ABB2BF"},"children":[{"type":"text","value":"({ "}]},{"type":"element","tag":"span","props":{"style":"--shiki-default:#E06C75"},"children":[{"type":"text","value":"url"}]},{"type":"element","tag":"span","props":{"style":"--shiki-default:#ABB2BF"},"children":[{"type":"text","value":", "}]},{"type":"element","tag":"span","props":{"style":"--shiki-default:#E06C75"},"children":[{"type":"text","value":"authToken"}]},{"type":"element","tag":"span","props":{"style":"--shiki-default:#ABB2BF"},"children":[{"type":"text","value":", "}]},{"type":"element","tag":"span","props":{"style":"--shiki-default:#E06C75"},"children":[{"type":"text","value":"fetch"}]},{"type":"element","tag":"span","props":{"style":"--shiki-default:#ABB2BF"},"children":[{"type":"text","value":": "}]},{"type":"element","tag":"span","props":{"style":"--shiki-default:#E06C75"},"children":[{"type":"text","value":"timeoutFetch"}]},{"type":"element","tag":"span","props":{"style":"--shiki-default:#ABB2BF"},"children":[{"type":"text","value":" })\n"}]}]}]}]},{"type":"element","tag":"p","props":{},"children":[{"type":"text","value":"abort 會真正銷毀連線、釋放 buffer；配合冪等的寫入（"},{"type":"element","tag":"code","props":{"className":[]},"children":[{"type":"text","value":"ON CONFLICT DO UPDATE"}]},{"type":"text","value":"），「盲目重試」是安全的。這裡還藏了一個彩蛋前提：abort 可能發生在「server 已經 commit、只是回應沒送達」的瞬間——你永遠無法分辨。寫入冪等是讓你"},{"type":"element","tag":"strong","props":{},"children":[{"type":"text","value":"不需要分辨"}]},{"type":"text","value":"的設計，這個主題值得獨立一篇（見系列第四篇）。"}]},{"type":"element","tag":"h2","props":{"id":"第三次修復本身變成兇器"},"children":[{"type":"text","value":"第三次：修復本身變成兇器"}]},{"type":"element","tag":"p","props":{},"children":[{"type":"text","value":"fetch 層的修法部署後 12 分鐘，"},{"type":"element","tag":"strong","props":{},"children":[{"type":"text","value":"每一個 DB 操作開始 crash"}]},{"type":"text","value":"："}]},{"type":"element","tag":"pre","props":{"code":"TypeError: Failed to parse URL from [object Request]\n"},"children":[{"type":"element","tag":"code","props":{"__ignoreMap":""},"children":[{"type":"text","value":"TypeError: Failed to parse URL from [object Request]\n"}]}]},{"type":"element","tag":"p","props":{},"children":[{"type":"text","value":"原因藏在抽象層的縫隙裡。libSQL 的底層協議 client（hrana）呼叫 fetch 時，傳進來的不是 URL 字串，而是 "},{"type":"element","tag":"strong","props":{},"children":[{"type":"text","value":"cross-fetch 的 "},{"type":"element","tag":"code","props":{"className":[]},"children":[{"type":"text","value":"Request"}]},{"type":"text","value":" 物件"}]},{"type":"text","value":"（Node 上是 node-fetch 的實作）。我的 "},{"type":"element","tag":"code","props":{"className":[]},"children":[{"type":"text","value":"timeoutFetch"}]},{"type":"text","value":" 把這個「外來實作」的 Request 直接轉給 Node 原生的 fetch（undici）——undici 不認得它，對它執行 "},{"type":"element","tag":"code","props":{"className":[]},"children":[{"type":"text","value":"new Request()"}]},{"type":"text","value":" → "},{"type":"element","tag":"code","props":{"className":[]},"children":[{"type":"text","value":"new URL(input)"}]},{"type":"text","value":"，把整個物件字串化成 "},{"type":"element","tag":"code","props":{"className":[]},"children":[{"type":"text","value":"[object Request]"}]},{"type":"text","value":"，爆炸。"}]},{"type":"element","tag":"p","props":{},"children":[{"type":"text","value":"修法：不讓非原生物件跨越實作邊界。把 Request 拆成原生欄位重組："}]},{"type":"element","tag":"pre","props":{"code":"resp = await fetch(input.url, {\n  method: input.method,\n  headers: [...input.headers],\n  body: input.method === 'GET' ? undefined : await input.arrayBuffer(),\n  signal: controller.signal,\n})\n","language":"ts","meta":"","className":"language-ts shiki shiki-themes one-dark-pro","style":""},"children":[{"type":"element","tag":"code","props":{"__ignoreMap":""},"children":[{"type":"element","tag":"span","props":{"class":"line","line":1},"children":[{"type":"element","tag":"span","props":{"style":"--shiki-default:#E06C75"},"children":[{"type":"text","value":"resp"}]},{"type":"element","tag":"span","props":{"style":"--shiki-default:#56B6C2"},"children":[{"type":"text","value":" ="}]},{"type":"element","tag":"span","props":{"style":"--shiki-default:#C678DD"},"children":[{"type":"text","value":" await"}]},{"type":"element","tag":"span","props":{"style":"--shiki-default:#61AFEF"},"children":[{"type":"text","value":" fetch"}]},{"type":"element","tag":"span","props":{"style":"--shiki-default:#ABB2BF"},"children":[{"type":"text","value":"("}]},{"type":"element","tag":"span","props":{"style":"--shiki-default:#E5C07B"},"children":[{"type":"text","value":"input"}]},{"type":"element","tag":"span","props":{"style":"--shiki-default:#ABB2BF"},"children":[{"type":"text","value":"."}]},{"type":"element","tag":"span","props":{"style":"--shiki-default:#E06C75"},"children":[{"type":"text","value":"url"}]},{"type":"element","tag":"span","props":{"style":"--shiki-default:#ABB2BF"},"children":[{"type":"text","value":", {\n"}]}]},{"type":"element","tag":"span","props":{"class":"line","line":2},"children":[{"type":"element","tag":"span","props":{"style":"--shiki-default:#E06C75"},"children":[{"type":"text","value":"  method"}]},{"type":"element","tag":"span","props":{"style":"--shiki-default:#ABB2BF"},"children":[{"type":"text","value":": "}]},{"type":"element","tag":"span","props":{"style":"--shiki-default:#E5C07B"},"children":[{"type":"text","value":"input"}]},{"type":"element","tag":"span","props":{"style":"--shiki-default:#ABB2BF"},"children":[{"type":"text","value":"."}]},{"type":"element","tag":"span","props":{"style":"--shiki-default:#E06C75"},"children":[{"type":"text","value":"method"}]},{"type":"element","tag":"span","props":{"style":"--shiki-default:#ABB2BF"},"children":[{"type":"text","value":",\n"}]}]},{"type":"element","tag":"span","props":{"class":"line","line":3},"children":[{"type":"element","tag":"span","props":{"style":"--shiki-default:#E06C75"},"children":[{"type":"text","value":"  headers"}]},{"type":"element","tag":"span","props":{"style":"--shiki-default:#ABB2BF"},"children":[{"type":"text","value":": [..."}]},{"type":"element","tag":"span","props":{"style":"--shiki-default:#E5C07B"},"children":[{"type":"text","value":"input"}]},{"type":"element","tag":"span","props":{"style":"--shiki-default:#ABB2BF"},"children":[{"type":"text","value":"."}]},{"type":"element","tag":"span","props":{"style":"--shiki-default:#E06C75"},"children":[{"type":"text","value":"headers"}]},{"type":"element","tag":"span","props":{"style":"--shiki-default:#ABB2BF"},"children":[{"type":"text","value":"],\n"}]}]},{"type":"element","tag":"span","props":{"class":"line","line":4},"children":[{"type":"element","tag":"span","props":{"style":"--shiki-default:#E06C75"},"children":[{"type":"text","value":"  body"}]},{"type":"element","tag":"span","props":{"style":"--shiki-default:#ABB2BF"},"children":[{"type":"text","value":": "}]},{"type":"element","tag":"span","props":{"style":"--shiki-default:#E5C07B"},"children":[{"type":"text","value":"input"}]},{"type":"element","tag":"span","props":{"style":"--shiki-default:#ABB2BF"},"children":[{"type":"text","value":"."}]},{"type":"element","tag":"span","props":{"style":"--shiki-default:#E06C75"},"children":[{"type":"text","value":"method"}]},{"type":"element","tag":"span","props":{"style":"--shiki-default:#56B6C2"},"children":[{"type":"text","value":" ==="}]},{"type":"element","tag":"span","props":{"style":"--shiki-default:#98C379"},"children":[{"type":"text","value":" 'GET'"}]},{"type":"element","tag":"span","props":{"style":"--shiki-default:#C678DD"},"children":[{"type":"text","value":" ?"}]},{"type":"element","tag":"span","props":{"style":"--shiki-default:#D19A66"},"children":[{"type":"text","value":" undefined"}]},{"type":"element","tag":"span","props":{"style":"--shiki-default:#C678DD"},"children":[{"type":"text","value":" :"}]},{"type":"element","tag":"span","props":{"style":"--shiki-default:#C678DD"},"children":[{"type":"text","value":" await"}]},{"type":"element","tag":"span","props":{"style":"--shiki-default:#E5C07B"},"children":[{"type":"text","value":" input"}]},{"type":"element","tag":"span","props":{"style":"--shiki-default:#ABB2BF"},"children":[{"type":"text","value":"."}]},{"type":"element","tag":"span","props":{"style":"--shiki-default:#61AFEF"},"children":[{"type":"text","value":"arrayBuffer"}]},{"type":"element","tag":"span","props":{"style":"--shiki-default:#ABB2BF"},"children":[{"type":"text","value":"(),\n"}]}]},{"type":"element","tag":"span","props":{"class":"line","line":5},"children":[{"type":"element","tag":"span","props":{"style":"--shiki-default:#E06C75"},"children":[{"type":"text","value":"  signal"}]},{"type":"element","tag":"span","props":{"style":"--shiki-default:#ABB2BF"},"children":[{"type":"text","value":": "}]},{"type":"element","tag":"span","props":{"style":"--shiki-default:#E5C07B"},"children":[{"type":"text","value":"controller"}]},{"type":"element","tag":"span","props":{"style":"--shiki-default:#ABB2BF"},"children":[{"type":"text","value":"."}]},{"type":"element","tag":"span","props":{"style":"--shiki-default:#E06C75"},"children":[{"type":"text","value":"signal"}]},{"type":"element","tag":"span","props":{"style":"--shiki-default:#ABB2BF"},"children":[{"type":"text","value":",\n"}]}]},{"type":"element","tag":"span","props":{"class":"line","line":6},"children":[{"type":"element","tag":"span","props":{"style":"--shiki-default:#ABB2BF"},"children":[{"type":"text","value":"})\n"}]}]}]}]},{"type":"element","tag":"p","props":{},"children":[{"type":"text","value":"另外補一刀：連 response body 也要在 timer 還活著時讀完（"},{"type":"element","tag":"code","props":{"className":[]},"children":[{"type":"text","value":"await resp.arrayBuffer()"}]},{"type":"text","value":" 再重組成 Response 返回），否則「server 送了 headers 卻卡住 body」的情況會漏出 timeout 的保護傘。"},{"type":"element","tag":"strong","props":{},"children":[{"type":"text","value":"timeout 要涵蓋 connection → headers → body 的整段"}]},{"type":"text","value":"，不是只有連上為止。"}]},{"type":"element","tag":"p","props":{},"children":[{"type":"text","value":"這次事故是 Joel Spolsky「漏水抽象定律」的完美標本："},{"type":"element","tag":"code","props":{"className":[]},"children":[{"type":"text","value":"createClient"}]},{"type":"text","value":" 的抽象讓你以為你只是在「用資料庫」，直到失效發生，你被迫下潛到 wire protocol 和 fetch 實作的層次。你不需要預先學會每一層，但需要在漏水時有能力往下潛一層——我最後是直接讀 "},{"type":"element","tag":"code","props":{"className":[]},"children":[{"type":"text","value":"node_modules"}]},{"type":"text","value":" 裡 hrana client 的原始碼對答案的。"}]},{"type":"element","tag":"h2","props":{"id":"尾聲從事故到日常"},"children":[{"type":"text","value":"尾聲：從事故到日常"}]},{"type":"element","tag":"p","props":{},"children":[{"type":"text","value":"三次修復全部落地後，有趣的事情發生了：log 顯示"},{"type":"element","tag":"strong","props":{},"children":[{"type":"text","value":"那個 black-hole 其實每天開盤都在發生"}]},{"type":"text","value":"——開盤後的第一發大量寫入（約 3.8 萬筆的 batch）幾乎必卡，只是現在它的結局從「凍死/OOM」變成：60 秒 timeout → abort 釋放 → 30 秒後重試 → 成功。全自動，代價 95 秒。"}]},{"type":"element","tag":"p","props":{},"children":[{"type":"text","value":"最後一手是把這 95 秒也消滅掉："},{"type":"element","tag":"strong","props":{},"children":[{"type":"text","value":"把爬蟲的啟動時間從開盤那一刻提前五分鐘"}]},{"type":"text","value":"。暖機、大寫入、可能的 stall 和重試，全部在開盤前消化完畢——不是縮短損失，是把損失移出交易時段。上線隔天驗證：開盤第一分鐘資料就開始流動。"}]},{"type":"element","tag":"p","props":{},"children":[{"type":"text","value":"三個帶得走的原則："}]},{"type":"element","tag":"ol","props":{},"children":[{"type":"element","tag":"li","props":{},"children":[{"type":"element","tag":"strong","props":{},"children":[{"type":"text","value":"timeout 不等於 abort。"}]},{"type":"text","value":" "},{"type":"element","tag":"code","props":{"className":[]},"children":[{"type":"text","value":"Promise.race"}]},{"type":"text","value":" 只是不等，"},{"type":"element","tag":"code","props":{"className":[]},"children":[{"type":"text","value":"AbortController"}]},{"type":"text","value":" 才是中止。不中止的 timeout 在重試迴圈裡就是記憶體洩漏製造機。"}]},{"type":"element","tag":"li","props":{},"children":[{"type":"element","tag":"strong","props":{},"children":[{"type":"text","value":"依賴出不出包不可控，放大倍率可控。"}]},{"type":"text","value":" 資料庫 black-hole 的合理代價是「outage 期間沒資料」；讓它變成「凍死 12 小時 + 手動重開」的是我自己的設計——單迴圈無 timeout、stop 依賴迴圈存活、timeout 不釋放資源，每一層都是放大器。"}]},{"type":"element","tag":"li","props":{},"children":[{"type":"element","tag":"strong","props":{},"children":[{"type":"text","value":"讓盲目重試是安全的，然後盡量重試。"}]},{"type":"text","value":" 冪等寫入 + 真正的 abort + 永不放棄的迴圈，是這個系統現在能在依賴發瘋時自癒的全部秘密。"}]}]},{"type":"element","tag":"h2","props":{"id":"環境資訊"},"children":[{"type":"text","value":"環境資訊"}]},{"type":"element","tag":"ul","props":{},"children":[{"type":"element","tag":"li","props":{},"children":[{"type":"text","value":"Node.js: v22.x（undici fetch）"}]},{"type":"element","tag":"li","props":{},"children":[{"type":"text","value":"@libsql/client: 0.17.x / @libsql/hrana-client: 0.9.x"}]},{"type":"element","tag":"li","props":{},"children":[{"type":"text","value":"Database: Turso（libSQL over HTTP）"}]},{"type":"element","tag":"li","props":{},"children":[{"type":"text","value":"Runtime: Fly.io"}]}]},{"type":"element","tag":"blockquote","props":{},"children":[{"type":"element","tag":"p","props":{},"children":[{"type":"text","value":"本文撰寫時間：2026 年 7 月，技術版本可能隨時間更新，請以官方文件為準。"}]}]},{"type":"element","tag":"section","props":{"className":["footnotes"],"dataFootnotes":""},"children":[{"type":"element","tag":"h2","props":{"className":["sr-only"],"id":"footnote-label"},"children":[{"type":"text","value":"Reference"}]},{"type":"element","tag":"ol","props":{},"children":[{"type":"element","tag":"li","props":{"id":"user-content-fn-1"},"children":[{"type":"element","tag":"a","props":{"href":"https://developer.mozilla.org/en-US/docs/Web/JavaScript/Reference/Global_Objects/Promise/race","rel":["nofollow"]},"children":[{"type":"text","value":"Promise.race() - JavaScript | MDN"}]},{"type":"text","value":" — race 以第一個 settle 的 promise 決定結果，但其他 promise 仍會繼續執行，不會被取消。 "},{"type":"element","tag":"a","props":{"href":"#user-content-fnref-1","ariaLabel":"Back to reference 1","className":["data-footnote-backref"],"dataFootnoteBackref":""},"children":[{"type":"text","value":"↩"}]}]},{"type":"element","tag":"li","props":{"id":"user-content-fn-2"},"children":[{"type":"element","tag":"a","props":{"href":"https://developer.mozilla.org/en-US/docs/Web/API/AbortController","rel":["nofollow"]},"children":[{"type":"text","value":"AbortController - Web APIs | MDN"}]},{"type":"text","value":" — 對 fetch 傳入 "},{"type":"element","tag":"code","props":{"className":[]},"children":[{"type":"text","value":"signal"}]},{"type":"text","value":" 後呼叫 "},{"type":"element","tag":"code","props":{"className":[]},"children":[{"type":"text","value":"abort()"}]},{"type":"text","value":"，會真正中斷請求並以 reason 拒絕該 promise。 "},{"type":"element","tag":"a","props":{"href":"#user-content-fnref-2","ariaLabel":"Back to reference 2","className":["data-footnote-backref"],"dataFootnoteBackref":""},"children":[{"type":"text","value":"↩"}]}]}]}]},{"type":"element","tag":"style","props":{},"children":[{"type":"text","value":"html .default .shiki span {color: var(--shiki-default);background: var(--shiki-default-bg);font-style: var(--shiki-default-font-style);font-weight: var(--shiki-default-font-weight);text-decoration: var(--shiki-default-text-decoration);}html .shiki span {color: var(--shiki-default);background: var(--shiki-default-bg);font-style: var(--shiki-default-font-style);font-weight: var(--shiki-default-font-weight);text-decoration: var(--shiki-default-text-decoration);}"}]}],"toc":{"title":"","searchDepth":2,"depth":2,"links":[{"id":"第一次凍死-12-小時","depth":2,"text":"第一次：凍死 12 小時"},{"id":"第二次oom","depth":2,"text":"第二次：OOM"},{"id":"第三次修復本身變成兇器","depth":2,"text":"第三次：修復本身變成兇器"},{"id":"尾聲從事故到日常","depth":2,"text":"尾聲：從事故到日常"},{"id":"環境資訊","depth":2,"text":"環境資訊"},{"id":"footnote-label","depth":2,"text":"Reference"}]}},"_type":"markdown","_id":"content:post:20260703-turso-blackhole-timeout-abort-postmortem.md","_source":"content","_file":"post/20260703-turso-blackhole-timeout-abort-postmortem.md","_stem":"post/20260703-turso-blackhole-timeout-abort-postmortem","_extension":"md","createdAt":"2026-07-03T04:01:52.000Z","updatedAt":"2026-07-03T09:44:39.000Z"}