{"_path":"/post/20260325-nuxt3-layout-height-management","_dir":"post","_draft":false,"_partial":false,"_locale":"","title":"Nuxt 3 Layout 與 Page 的高度職責分離：解決多餘 scrollbar 問題","description":"在 Nuxt 3 的 SPA 專案中，Layout 與 Page 之間的高度管理是個容易踩坑的地方。本文記錄一個常見問題：各個 Page 各自用 h-screen 控制高度，導致出現多餘的外層 scrollbar，以及修正過程中學到的 CSS 定位觀念。","tags":"vue, nuxt, nuxt3, css, unocss, layout, 前端開發, 技術筆記","createdByAI":true,"readingTime":{"text":"5 min read","minutes":4.145,"time":248700,"words":829},"body":{"type":"root","children":[{"type":"element","tag":"p","props":{},"children":[{"type":"text","value":"在 Nuxt 3 的 SPA 專案中，Layout 與 Page 之間的高度管理是個容易踩坑的地方。本文記錄一個常見問題：各個 Page 各自用 "},{"type":"element","tag":"code","props":{"className":[]},"children":[{"type":"text","value":"h-screen"}]},{"type":"text","value":" 控制高度，導致出現多餘的外層 scrollbar，以及修正過程中學到的 CSS 定位觀念。"}]},{"type":"element","tag":"h2","props":{"id":"問題描述"},"children":[{"type":"text","value":"問題描述"}]},{"type":"element","tag":"p","props":{},"children":[{"type":"text","value":"專案的 "},{"type":"element","tag":"code","props":{"className":[]},"children":[{"type":"text","value":"default.vue"}]},{"type":"text","value":" layout 結構大致如下："}]},{"type":"element","tag":"pre","props":{"className":"language-html shiki shiki-themes one-dark-pro","code":"<div class=\"min-h-screen flex flex-col\">\n  <!-- 公告列，固定高度 -->\n  <div class=\"h-18\">...</div>\n\n  <!-- 主區塊：側邊欄 + 頁面內容 -->\n  <div class=\"flex\">\n    <SideNav />\n    <div class=\"flex-1\">\n      <slot />\n    </div>\n  </div>\n</div>\n","language":"html","meta":"","style":""},"children":[{"type":"element","tag":"code","props":{"__ignoreMap":""},"children":[{"type":"element","tag":"span","props":{"class":"line","line":1},"children":[{"type":"element","tag":"span","props":{"style":"--shiki-default:#ABB2BF"},"children":[{"type":"text","value":"<"}]},{"type":"element","tag":"span","props":{"style":"--shiki-default:#E06C75"},"children":[{"type":"text","value":"div"}]},{"type":"element","tag":"span","props":{"style":"--shiki-default:#D19A66"},"children":[{"type":"text","value":" class"}]},{"type":"element","tag":"span","props":{"style":"--shiki-default:#ABB2BF"},"children":[{"type":"text","value":"="}]},{"type":"element","tag":"span","props":{"style":"--shiki-default:#98C379"},"children":[{"type":"text","value":"\"min-h-screen flex flex-col\""}]},{"type":"element","tag":"span","props":{"style":"--shiki-default:#ABB2BF"},"children":[{"type":"text","value":">\n"}]}]},{"type":"element","tag":"span","props":{"class":"line","line":2},"children":[{"type":"element","tag":"span","props":{"style":"--shiki-default:#7F848E;--shiki-default-font-style:italic"},"children":[{"type":"text","value":"  <!-- 公告列，固定高度 -->\n"}]}]},{"type":"element","tag":"span","props":{"class":"line","line":3},"children":[{"type":"element","tag":"span","props":{"style":"--shiki-default:#ABB2BF"},"children":[{"type":"text","value":"  <"}]},{"type":"element","tag":"span","props":{"style":"--shiki-default:#E06C75"},"children":[{"type":"text","value":"div"}]},{"type":"element","tag":"span","props":{"style":"--shiki-default:#D19A66"},"children":[{"type":"text","value":" class"}]},{"type":"element","tag":"span","props":{"style":"--shiki-default:#ABB2BF"},"children":[{"type":"text","value":"="}]},{"type":"element","tag":"span","props":{"style":"--shiki-default:#98C379"},"children":[{"type":"text","value":"\"h-18\""}]},{"type":"element","tag":"span","props":{"style":"--shiki-default:#ABB2BF"},"children":[{"type":"text","value":">...</"}]},{"type":"element","tag":"span","props":{"style":"--shiki-default:#E06C75"},"children":[{"type":"text","value":"div"}]},{"type":"element","tag":"span","props":{"style":"--shiki-default:#ABB2BF"},"children":[{"type":"text","value":">\n"}]}]},{"type":"element","tag":"span","props":{"class":"line","line":4},"children":[{"type":"element","tag":"span","props":{"emptyLinePlaceholder":true},"children":[{"type":"text","value":"\n"}]}]},{"type":"element","tag":"span","props":{"class":"line","line":5},"children":[{"type":"element","tag":"span","props":{"style":"--shiki-default:#7F848E;--shiki-default-font-style:italic"},"children":[{"type":"text","value":"  <!-- 主區塊：側邊欄 + 頁面內容 -->\n"}]}]},{"type":"element","tag":"span","props":{"class":"line","line":6},"children":[{"type":"element","tag":"span","props":{"style":"--shiki-default:#ABB2BF"},"children":[{"type":"text","value":"  <"}]},{"type":"element","tag":"span","props":{"style":"--shiki-default:#E06C75"},"children":[{"type":"text","value":"div"}]},{"type":"element","tag":"span","props":{"style":"--shiki-default:#D19A66"},"children":[{"type":"text","value":" class"}]},{"type":"element","tag":"span","props":{"style":"--shiki-default:#ABB2BF"},"children":[{"type":"text","value":"="}]},{"type":"element","tag":"span","props":{"style":"--shiki-default:#98C379"},"children":[{"type":"text","value":"\"flex\""}]},{"type":"element","tag":"span","props":{"style":"--shiki-default:#ABB2BF"},"children":[{"type":"text","value":">\n"}]}]},{"type":"element","tag":"span","props":{"class":"line","line":7},"children":[{"type":"element","tag":"span","props":{"style":"--shiki-default:#ABB2BF"},"children":[{"type":"text","value":"    <"}]},{"type":"element","tag":"span","props":{"style":"--shiki-default:#E06C75"},"children":[{"type":"text","value":"SideNav"}]},{"type":"element","tag":"span","props":{"style":"--shiki-default:#ABB2BF"},"children":[{"type":"text","value":" />\n"}]}]},{"type":"element","tag":"span","props":{"class":"line","line":8},"children":[{"type":"element","tag":"span","props":{"style":"--shiki-default:#ABB2BF"},"children":[{"type":"text","value":"    <"}]},{"type":"element","tag":"span","props":{"style":"--shiki-default:#E06C75"},"children":[{"type":"text","value":"div"}]},{"type":"element","tag":"span","props":{"style":"--shiki-default:#D19A66"},"children":[{"type":"text","value":" class"}]},{"type":"element","tag":"span","props":{"style":"--shiki-default:#ABB2BF"},"children":[{"type":"text","value":"="}]},{"type":"element","tag":"span","props":{"style":"--shiki-default:#98C379"},"children":[{"type":"text","value":"\"flex-1\""}]},{"type":"element","tag":"span","props":{"style":"--shiki-default:#ABB2BF"},"children":[{"type":"text","value":">\n"}]}]},{"type":"element","tag":"span","props":{"class":"line","line":9},"children":[{"type":"element","tag":"span","props":{"style":"--shiki-default:#ABB2BF"},"children":[{"type":"text","value":"      <"}]},{"type":"element","tag":"span","props":{"style":"--shiki-default:#E06C75"},"children":[{"type":"text","value":"slot"}]},{"type":"element","tag":"span","props":{"style":"--shiki-default:#FFFFFF"},"children":[{"type":"text","value":" /"}]},{"type":"element","tag":"span","props":{"style":"--shiki-default:#ABB2BF"},"children":[{"type":"text","value":">\n"}]}]},{"type":"element","tag":"span","props":{"class":"line","line":10},"children":[{"type":"element","tag":"span","props":{"style":"--shiki-default:#ABB2BF"},"children":[{"type":"text","value":"    </"}]},{"type":"element","tag":"span","props":{"style":"--shiki-default:#E06C75"},"children":[{"type":"text","value":"div"}]},{"type":"element","tag":"span","props":{"style":"--shiki-default:#ABB2BF"},"children":[{"type":"text","value":">\n"}]}]},{"type":"element","tag":"span","props":{"class":"line","line":11},"children":[{"type":"element","tag":"span","props":{"style":"--shiki-default:#ABB2BF"},"children":[{"type":"text","value":"  </"}]},{"type":"element","tag":"span","props":{"style":"--shiki-default:#E06C75"},"children":[{"type":"text","value":"div"}]},{"type":"element","tag":"span","props":{"style":"--shiki-default:#ABB2BF"},"children":[{"type":"text","value":">\n"}]}]},{"type":"element","tag":"span","props":{"class":"line","line":12},"children":[{"type":"element","tag":"span","props":{"style":"--shiki-default:#ABB2BF"},"children":[{"type":"text","value":"</"}]},{"type":"element","tag":"span","props":{"style":"--shiki-default:#E06C75"},"children":[{"type":"text","value":"div"}]},{"type":"element","tag":"span","props":{"style":"--shiki-default:#ABB2BF"},"children":[{"type":"text","value":">\n"}]}]}]}]},{"type":"element","tag":"p","props":{},"children":[{"type":"text","value":"各個 Page 的最外層則是："}]},{"type":"element","tag":"pre","props":{"className":"language-html shiki shiki-themes one-dark-pro","code":"<div class=\"h-screen overflow-y-auto ...\">\n  <!-- 頁面內容 -->\n</div>\n","language":"html","meta":"","style":""},"children":[{"type":"element","tag":"code","props":{"__ignoreMap":""},"children":[{"type":"element","tag":"span","props":{"class":"line","line":1},"children":[{"type":"element","tag":"span","props":{"style":"--shiki-default:#ABB2BF"},"children":[{"type":"text","value":"<"}]},{"type":"element","tag":"span","props":{"style":"--shiki-default:#E06C75"},"children":[{"type":"text","value":"div"}]},{"type":"element","tag":"span","props":{"style":"--shiki-default:#D19A66"},"children":[{"type":"text","value":" class"}]},{"type":"element","tag":"span","props":{"style":"--shiki-default:#ABB2BF"},"children":[{"type":"text","value":"="}]},{"type":"element","tag":"span","props":{"style":"--shiki-default:#98C379"},"children":[{"type":"text","value":"\"h-screen overflow-y-auto ...\""}]},{"type":"element","tag":"span","props":{"style":"--shiki-default:#ABB2BF"},"children":[{"type":"text","value":">\n"}]}]},{"type":"element","tag":"span","props":{"class":"line","line":2},"children":[{"type":"element","tag":"span","props":{"style":"--shiki-default:#7F848E;--shiki-default-font-style:italic"},"children":[{"type":"text","value":"  <!-- 頁面內容 -->\n"}]}]},{"type":"element","tag":"span","props":{"class":"line","line":3},"children":[{"type":"element","tag":"span","props":{"style":"--shiki-default:#ABB2BF"},"children":[{"type":"text","value":"</"}]},{"type":"element","tag":"span","props":{"style":"--shiki-default:#E06C75"},"children":[{"type":"text","value":"div"}]},{"type":"element","tag":"span","props":{"style":"--shiki-default:#ABB2BF"},"children":[{"type":"text","value":">\n"}]}]}]}]},{"type":"element","tag":"p","props":{},"children":[{"type":"text","value":"結果：頁面出現兩層 scrollbar，外層 body 也會滾動。"}]},{"type":"element","tag":"h2","props":{"id":"根本原因分析"},"children":[{"type":"text","value":"根本原因分析"}]},{"type":"element","tag":"h3","props":{"id":"h-screen-與-h-full-的差異"},"children":[{"type":"text","value":"h-screen 與 h-full 的差異"}]},{"type":"element","tag":"p","props":{},"children":[{"type":"element","tag":"code","props":{"className":[]},"children":[{"type":"text","value":"h-screen"}]},{"type":"text","value":" 等同於 "},{"type":"element","tag":"code","props":{"className":[]},"children":[{"type":"text","value":"height: 100vh"}]},{"type":"text","value":"，高度固定參考視窗高度，與父層給多少空間無關。"}]},{"type":"element","tag":"p","props":{},"children":[{"type":"element","tag":"code","props":{"className":[]},"children":[{"type":"text","value":"h-full"}]},{"type":"text","value":" 等同於 "},{"type":"element","tag":"code","props":{"className":[]},"children":[{"type":"text","value":"height: 100%"}]},{"type":"text","value":"，繼承父層分配的高度。"}]},{"type":"element","tag":"p","props":{},"children":[{"type":"text","value":"在這個 layout 裡，"},{"type":"element","tag":"code","props":{"className":[]},"children":[{"type":"text","value":"<slot />"}]},{"type":"text","value":" 的父層只有「視窗高度 - 公告列高度」的空間，但 Page 用 "},{"type":"element","tag":"code","props":{"className":[]},"children":[{"type":"text","value":"h-screen"}]},{"type":"text","value":" 自己撐成整個視窗高，內容溢出後 scrollbar 就跑到外層去了。"}]},{"type":"element","tag":"h3","props":{"id":"overflow-y-auto-需要明確的高度限制"},"children":[{"type":"text","value":"overflow-y: auto 需要明確的高度限制"}]},{"type":"element","tag":"p","props":{},"children":[{"type":"element","tag":"code","props":{"className":[]},"children":[{"type":"text","value":"overflow-y: auto"}]},{"type":"text","value":" 要能生效，元素必須有明確的高度上限"},{"type":"element","tag":"sup","props":{},"children":[{"type":"element","tag":"a","props":{"href":"#user-content-fn-1","ariaDescribedBy":["footnote-label"],"dataFootnoteRef":"","id":"user-content-fnref-1"},"children":[{"type":"text","value":"1"}]}]},{"type":"text","value":"。"}]},{"type":"element","tag":"ul","props":{},"children":[{"type":"element","tag":"li","props":{},"children":[{"type":"element","tag":"code","props":{"className":[]},"children":[{"type":"text","value":"h-auto"}]},{"type":"text","value":"：高度由內容撐開，沒有上限，"},{"type":"element","tag":"code","props":{"className":[]},"children":[{"type":"text","value":"overflow-y: auto"}]},{"type":"text","value":" 永遠不會觸發"}]},{"type":"element","tag":"li","props":{},"children":[{"type":"element","tag":"code","props":{"className":[]},"children":[{"type":"text","value":"h-full"}]},{"type":"text","value":"：繼承父層高度，提供了明確的高度約束，scrollbar 才會出現在元素內部"}]}]},{"type":"element","tag":"h2","props":{"id":"修正方案"},"children":[{"type":"text","value":"修正方案"}]},{"type":"element","tag":"h3","props":{"id":"layout-層鎖死高度邊界"},"children":[{"type":"text","value":"Layout 層：鎖死高度邊界"}]},{"type":"element","tag":"pre","props":{"className":"language-html shiki shiki-themes one-dark-pro","code":"<div class=\"h-screen flex flex-col overflow-hidden\">\n  <div v-if=\"showAnnouncement\" class=\"h-18 shrink-0\">\n    <!-- 公告列 -->\n  </div>\n\n  <div class=\"flex flex-1 overflow-hidden\">\n    <SideNav />\n    <div class=\"flex-1 overflow-y-auto\">\n      <slot />\n    </div>\n  </div>\n</div>\n","language":"html","meta":"","style":""},"children":[{"type":"element","tag":"code","props":{"__ignoreMap":""},"children":[{"type":"element","tag":"span","props":{"class":"line","line":1},"children":[{"type":"element","tag":"span","props":{"style":"--shiki-default:#ABB2BF"},"children":[{"type":"text","value":"<"}]},{"type":"element","tag":"span","props":{"style":"--shiki-default:#E06C75"},"children":[{"type":"text","value":"div"}]},{"type":"element","tag":"span","props":{"style":"--shiki-default:#D19A66"},"children":[{"type":"text","value":" class"}]},{"type":"element","tag":"span","props":{"style":"--shiki-default:#ABB2BF"},"children":[{"type":"text","value":"="}]},{"type":"element","tag":"span","props":{"style":"--shiki-default:#98C379"},"children":[{"type":"text","value":"\"h-screen flex flex-col overflow-hidden\""}]},{"type":"element","tag":"span","props":{"style":"--shiki-default:#ABB2BF"},"children":[{"type":"text","value":">\n"}]}]},{"type":"element","tag":"span","props":{"class":"line","line":2},"children":[{"type":"element","tag":"span","props":{"style":"--shiki-default:#ABB2BF"},"children":[{"type":"text","value":"  <"}]},{"type":"element","tag":"span","props":{"style":"--shiki-default:#E06C75"},"children":[{"type":"text","value":"div"}]},{"type":"element","tag":"span","props":{"style":"--shiki-default:#D19A66"},"children":[{"type":"text","value":" v-if"}]},{"type":"element","tag":"span","props":{"style":"--shiki-default:#ABB2BF"},"children":[{"type":"text","value":"="}]},{"type":"element","tag":"span","props":{"style":"--shiki-default:#98C379"},"children":[{"type":"text","value":"\"showAnnouncement\""}]},{"type":"element","tag":"span","props":{"style":"--shiki-default:#D19A66"},"children":[{"type":"text","value":" class"}]},{"type":"element","tag":"span","props":{"style":"--shiki-default:#ABB2BF"},"children":[{"type":"text","value":"="}]},{"type":"element","tag":"span","props":{"style":"--shiki-default:#98C379"},"children":[{"type":"text","value":"\"h-18 shrink-0\""}]},{"type":"element","tag":"span","props":{"style":"--shiki-default:#ABB2BF"},"children":[{"type":"text","value":">\n"}]}]},{"type":"element","tag":"span","props":{"class":"line","line":3},"children":[{"type":"element","tag":"span","props":{"style":"--shiki-default:#7F848E;--shiki-default-font-style:italic"},"children":[{"type":"text","value":"    <!-- 公告列 -->\n"}]}]},{"type":"element","tag":"span","props":{"class":"line","line":4},"children":[{"type":"element","tag":"span","props":{"style":"--shiki-default:#ABB2BF"},"children":[{"type":"text","value":"  </"}]},{"type":"element","tag":"span","props":{"style":"--shiki-default:#E06C75"},"children":[{"type":"text","value":"div"}]},{"type":"element","tag":"span","props":{"style":"--shiki-default:#ABB2BF"},"children":[{"type":"text","value":">\n"}]}]},{"type":"element","tag":"span","props":{"class":"line","line":5},"children":[{"type":"element","tag":"span","props":{"emptyLinePlaceholder":true},"children":[{"type":"text","value":"\n"}]}]},{"type":"element","tag":"span","props":{"class":"line","line":6},"children":[{"type":"element","tag":"span","props":{"style":"--shiki-default:#ABB2BF"},"children":[{"type":"text","value":"  <"}]},{"type":"element","tag":"span","props":{"style":"--shiki-default:#E06C75"},"children":[{"type":"text","value":"div"}]},{"type":"element","tag":"span","props":{"style":"--shiki-default:#D19A66"},"children":[{"type":"text","value":" class"}]},{"type":"element","tag":"span","props":{"style":"--shiki-default:#ABB2BF"},"children":[{"type":"text","value":"="}]},{"type":"element","tag":"span","props":{"style":"--shiki-default:#98C379"},"children":[{"type":"text","value":"\"flex flex-1 overflow-hidden\""}]},{"type":"element","tag":"span","props":{"style":"--shiki-default:#ABB2BF"},"children":[{"type":"text","value":">\n"}]}]},{"type":"element","tag":"span","props":{"class":"line","line":7},"children":[{"type":"element","tag":"span","props":{"style":"--shiki-default:#ABB2BF"},"children":[{"type":"text","value":"    <"}]},{"type":"element","tag":"span","props":{"style":"--shiki-default:#E06C75"},"children":[{"type":"text","value":"SideNav"}]},{"type":"element","tag":"span","props":{"style":"--shiki-default:#ABB2BF"},"children":[{"type":"text","value":" />\n"}]}]},{"type":"element","tag":"span","props":{"class":"line","line":8},"children":[{"type":"element","tag":"span","props":{"style":"--shiki-default:#ABB2BF"},"children":[{"type":"text","value":"    <"}]},{"type":"element","tag":"span","props":{"style":"--shiki-default:#E06C75"},"children":[{"type":"text","value":"div"}]},{"type":"element","tag":"span","props":{"style":"--shiki-default:#D19A66"},"children":[{"type":"text","value":" class"}]},{"type":"element","tag":"span","props":{"style":"--shiki-default:#ABB2BF"},"children":[{"type":"text","value":"="}]},{"type":"element","tag":"span","props":{"style":"--shiki-default:#98C379"},"children":[{"type":"text","value":"\"flex-1 overflow-y-auto\""}]},{"type":"element","tag":"span","props":{"style":"--shiki-default:#ABB2BF"},"children":[{"type":"text","value":">\n"}]}]},{"type":"element","tag":"span","props":{"class":"line","line":9},"children":[{"type":"element","tag":"span","props":{"style":"--shiki-default:#ABB2BF"},"children":[{"type":"text","value":"      <"}]},{"type":"element","tag":"span","props":{"style":"--shiki-default:#E06C75"},"children":[{"type":"text","value":"slot"}]},{"type":"element","tag":"span","props":{"style":"--shiki-default:#FFFFFF"},"children":[{"type":"text","value":" /"}]},{"type":"element","tag":"span","props":{"style":"--shiki-default:#ABB2BF"},"children":[{"type":"text","value":">\n"}]}]},{"type":"element","tag":"span","props":{"class":"line","line":10},"children":[{"type":"element","tag":"span","props":{"style":"--shiki-default:#ABB2BF"},"children":[{"type":"text","value":"    </"}]},{"type":"element","tag":"span","props":{"style":"--shiki-default:#E06C75"},"children":[{"type":"text","value":"div"}]},{"type":"element","tag":"span","props":{"style":"--shiki-default:#ABB2BF"},"children":[{"type":"text","value":">\n"}]}]},{"type":"element","tag":"span","props":{"class":"line","line":11},"children":[{"type":"element","tag":"span","props":{"style":"--shiki-default:#ABB2BF"},"children":[{"type":"text","value":"  </"}]},{"type":"element","tag":"span","props":{"style":"--shiki-default:#E06C75"},"children":[{"type":"text","value":"div"}]},{"type":"element","tag":"span","props":{"style":"--shiki-default:#ABB2BF"},"children":[{"type":"text","value":">\n"}]}]},{"type":"element","tag":"span","props":{"class":"line","line":12},"children":[{"type":"element","tag":"span","props":{"style":"--shiki-default:#ABB2BF"},"children":[{"type":"text","value":"</"}]},{"type":"element","tag":"span","props":{"style":"--shiki-default:#E06C75"},"children":[{"type":"text","value":"div"}]},{"type":"element","tag":"span","props":{"style":"--shiki-default:#ABB2BF"},"children":[{"type":"text","value":">\n"}]}]}]}]},{"type":"element","tag":"p","props":{},"children":[{"type":"text","value":"關鍵改動："}]},{"type":"element","tag":"ul","props":{},"children":[{"type":"element","tag":"li","props":{},"children":[{"type":"text","value":"最外層從 "},{"type":"element","tag":"code","props":{"className":[]},"children":[{"type":"text","value":"min-h-screen"}]},{"type":"text","value":" 改為 "},{"type":"element","tag":"code","props":{"className":[]},"children":[{"type":"text","value":"h-screen overflow-hidden"}]},{"type":"text","value":"，鎖死視窗高度"}]},{"type":"element","tag":"li","props":{},"children":[{"type":"text","value":"主區塊加 "},{"type":"element","tag":"code","props":{"className":[]},"children":[{"type":"text","value":"flex-1 overflow-hidden"}]},{"type":"text","value":"，填滿剩餘空間並防止溢出"}]},{"type":"element","tag":"li","props":{},"children":[{"type":"element","tag":"code","props":{"className":[]},"children":[{"type":"text","value":"<slot />"}]},{"type":"text","value":" 的容器加 "},{"type":"element","tag":"code","props":{"className":[]},"children":[{"type":"text","value":"overflow-y-auto"}]},{"type":"text","value":"，讓 Page 的滾動發生在這裡"}]}]},{"type":"element","tag":"h3","props":{"id":"page-層改用-h-full"},"children":[{"type":"text","value":"Page 層：改用 h-full"}]},{"type":"element","tag":"pre","props":{"className":"language-html shiki shiki-themes one-dark-pro","code":"<!-- 修改前 -->\n<div class=\"h-screen overflow-y-auto ...\">\n\n<!-- 修改後 -->\n<div class=\"h-full overflow-y-auto ...\">\n","language":"html","meta":"","style":""},"children":[{"type":"element","tag":"code","props":{"__ignoreMap":""},"children":[{"type":"element","tag":"span","props":{"class":"line","line":1},"children":[{"type":"element","tag":"span","props":{"style":"--shiki-default:#7F848E;--shiki-default-font-style:italic"},"children":[{"type":"text","value":"<!-- 修改前 -->\n"}]}]},{"type":"element","tag":"span","props":{"class":"line","line":2},"children":[{"type":"element","tag":"span","props":{"style":"--shiki-default:#ABB2BF"},"children":[{"type":"text","value":"<"}]},{"type":"element","tag":"span","props":{"style":"--shiki-default:#E06C75"},"children":[{"type":"text","value":"div"}]},{"type":"element","tag":"span","props":{"style":"--shiki-default:#D19A66"},"children":[{"type":"text","value":" class"}]},{"type":"element","tag":"span","props":{"style":"--shiki-default:#ABB2BF"},"children":[{"type":"text","value":"="}]},{"type":"element","tag":"span","props":{"style":"--shiki-default:#98C379"},"children":[{"type":"text","value":"\"h-screen overflow-y-auto ...\""}]},{"type":"element","tag":"span","props":{"style":"--shiki-default:#ABB2BF"},"children":[{"type":"text","value":">\n"}]}]},{"type":"element","tag":"span","props":{"class":"line","line":3},"children":[{"type":"element","tag":"span","props":{"emptyLinePlaceholder":true},"children":[{"type":"text","value":"\n"}]}]},{"type":"element","tag":"span","props":{"class":"line","line":4},"children":[{"type":"element","tag":"span","props":{"style":"--shiki-default:#7F848E;--shiki-default-font-style:italic"},"children":[{"type":"text","value":"<!-- 修改後 -->\n"}]}]},{"type":"element","tag":"span","props":{"class":"line","line":5},"children":[{"type":"element","tag":"span","props":{"style":"--shiki-default:#ABB2BF"},"children":[{"type":"text","value":"<"}]},{"type":"element","tag":"span","props":{"style":"--shiki-default:#E06C75"},"children":[{"type":"text","value":"div"}]},{"type":"element","tag":"span","props":{"style":"--shiki-default:#D19A66"},"children":[{"type":"text","value":" class"}]},{"type":"element","tag":"span","props":{"style":"--shiki-default:#ABB2BF"},"children":[{"type":"text","value":"="}]},{"type":"element","tag":"span","props":{"style":"--shiki-default:#98C379"},"children":[{"type":"text","value":"\"h-full overflow-y-auto ...\""}]},{"type":"element","tag":"span","props":{"style":"--shiki-default:#ABB2BF"},"children":[{"type":"text","value":">\n"}]}]}]}]},{"type":"element","tag":"p","props":{},"children":[{"type":"text","value":"Detail page 的 "},{"type":"element","tag":"code","props":{"className":[]},"children":[{"type":"text","value":"max-h-screen"}]},{"type":"text","value":" 同樣改為 "},{"type":"element","tag":"code","props":{"className":[]},"children":[{"type":"text","value":"h-full"}]},{"type":"text","value":"："}]},{"type":"element","tag":"pre","props":{"className":"language-html shiki shiki-themes one-dark-pro","code":"<!-- 修改前 -->\n<div class=\"max-h-screen overflow-auto\">\n\n<!-- 修改後 -->\n<div class=\"h-full overflow-auto\">\n","language":"html","meta":"","style":""},"children":[{"type":"element","tag":"code","props":{"__ignoreMap":""},"children":[{"type":"element","tag":"span","props":{"class":"line","line":1},"children":[{"type":"element","tag":"span","props":{"style":"--shiki-default:#7F848E;--shiki-default-font-style:italic"},"children":[{"type":"text","value":"<!-- 修改前 -->\n"}]}]},{"type":"element","tag":"span","props":{"class":"line","line":2},"children":[{"type":"element","tag":"span","props":{"style":"--shiki-default:#ABB2BF"},"children":[{"type":"text","value":"<"}]},{"type":"element","tag":"span","props":{"style":"--shiki-default:#E06C75"},"children":[{"type":"text","value":"div"}]},{"type":"element","tag":"span","props":{"style":"--shiki-default:#D19A66"},"children":[{"type":"text","value":" class"}]},{"type":"element","tag":"span","props":{"style":"--shiki-default:#ABB2BF"},"children":[{"type":"text","value":"="}]},{"type":"element","tag":"span","props":{"style":"--shiki-default:#98C379"},"children":[{"type":"text","value":"\"max-h-screen overflow-auto\""}]},{"type":"element","tag":"span","props":{"style":"--shiki-default:#ABB2BF"},"children":[{"type":"text","value":">\n"}]}]},{"type":"element","tag":"span","props":{"class":"line","line":3},"children":[{"type":"element","tag":"span","props":{"emptyLinePlaceholder":true},"children":[{"type":"text","value":"\n"}]}]},{"type":"element","tag":"span","props":{"class":"line","line":4},"children":[{"type":"element","tag":"span","props":{"style":"--shiki-default:#7F848E;--shiki-default-font-style:italic"},"children":[{"type":"text","value":"<!-- 修改後 -->\n"}]}]},{"type":"element","tag":"span","props":{"class":"line","line":5},"children":[{"type":"element","tag":"span","props":{"style":"--shiki-default:#ABB2BF"},"children":[{"type":"text","value":"<"}]},{"type":"element","tag":"span","props":{"style":"--shiki-default:#E06C75"},"children":[{"type":"text","value":"div"}]},{"type":"element","tag":"span","props":{"style":"--shiki-default:#D19A66"},"children":[{"type":"text","value":" class"}]},{"type":"element","tag":"span","props":{"style":"--shiki-default:#ABB2BF"},"children":[{"type":"text","value":"="}]},{"type":"element","tag":"span","props":{"style":"--shiki-default:#98C379"},"children":[{"type":"text","value":"\"h-full overflow-auto\""}]},{"type":"element","tag":"span","props":{"style":"--shiki-default:#ABB2BF"},"children":[{"type":"text","value":">\n"}]}]}]}]},{"type":"element","tag":"h3","props":{"id":"職責分工"},"children":[{"type":"text","value":"職責分工"}]},{"type":"element","tag":"p","props":{},"children":[{"type":"text","value":"修正後的架構，職責清楚分離："}]},{"type":"element","tag":"ul","props":{},"children":[{"type":"element","tag":"li","props":{},"children":[{"type":"element","tag":"strong","props":{},"children":[{"type":"text","value":"Layout"}]},{"type":"text","value":"：負責定義整體高度邊界、切割空間"}]},{"type":"element","tag":"li","props":{},"children":[{"type":"element","tag":"strong","props":{},"children":[{"type":"text","value":"Page"}]},{"type":"text","value":"：只負責自己內部的排版和滾動，高度從 layout 繼承"}]}]},{"type":"element","tag":"p","props":{},"children":[{"type":"text","value":"好處是未來 layout 有變動（例如關掉公告列、加上 top bar），所有 Page 不需要跟著改，高度會自動重新分配。"}]},{"type":"element","tag":"h2","props":{"id":"延伸position-absolute-的對立方向拉伸"},"children":[{"type":"text","value":"延伸：position absolute 的對立方向拉伸"}]},{"type":"element","tag":"p","props":{},"children":[{"type":"text","value":"修正側邊欄時，學到一個實用的 CSS 行為："},{"type":"element","tag":"code","props":{"className":[]},"children":[{"type":"text","value":"position: absolute"}]},{"type":"text","value":" 或 "},{"type":"element","tag":"code","props":{"className":[]},"children":[{"type":"text","value":"fixed"}]},{"type":"text","value":" 的元素，當同時設定對立方向的 offset，瀏覽器會用「拉伸」來滿足兩個約束"},{"type":"element","tag":"sup","props":{},"children":[{"type":"element","tag":"a","props":{"href":"#user-content-fn-2","ariaDescribedBy":["footnote-label"],"dataFootnoteRef":"","id":"user-content-fnref-2"},"children":[{"type":"text","value":"2"}]}]},{"type":"text","value":"。"}]},{"type":"element","tag":"pre","props":{"className":"language-css shiki shiki-themes one-dark-pro","code":"/* 垂直拉伸，高度填滿定位祖先 */\nposition: absolute;\ntop: 0;\nbottom: 0;\n\n/* 水平拉伸，寬度填滿定位祖先 */\nposition: absolute;\nleft: 0;\nright: 0;\n\n/* 四邊都設，完全覆蓋父層（常見於 overlay） */\nposition: absolute;\ninset: 0;\n","language":"css","meta":"","style":""},"children":[{"type":"element","tag":"code","props":{"__ignoreMap":""},"children":[{"type":"element","tag":"span","props":{"class":"line","line":1},"children":[{"type":"element","tag":"span","props":{"style":"--shiki-default:#7F848E;--shiki-default-font-style:italic"},"children":[{"type":"text","value":"/* 垂直拉伸，高度填滿定位祖先 */\n"}]}]},{"type":"element","tag":"span","props":{"class":"line","line":2},"children":[{"type":"element","tag":"span","props":{"style":"--shiki-default:#C678DD"},"children":[{"type":"text","value":"position: absolute;\n"}]}]},{"type":"element","tag":"span","props":{"class":"line","line":3},"children":[{"type":"element","tag":"span","props":{"style":"--shiki-default:#C678DD"},"children":[{"type":"text","value":"top: 0;\n"}]}]},{"type":"element","tag":"span","props":{"class":"line","line":4},"children":[{"type":"element","tag":"span","props":{"style":"--shiki-default:#C678DD"},"children":[{"type":"text","value":"bottom: 0;\n"}]}]},{"type":"element","tag":"span","props":{"class":"line","line":5},"children":[{"type":"element","tag":"span","props":{"emptyLinePlaceholder":true},"children":[{"type":"text","value":"\n"}]}]},{"type":"element","tag":"span","props":{"class":"line","line":6},"children":[{"type":"element","tag":"span","props":{"style":"--shiki-default:#7F848E;--shiki-default-font-style:italic"},"children":[{"type":"text","value":"/* 水平拉伸，寬度填滿定位祖先 */\n"}]}]},{"type":"element","tag":"span","props":{"class":"line","line":7},"children":[{"type":"element","tag":"span","props":{"style":"--shiki-default:#C678DD"},"children":[{"type":"text","value":"position: absolute;\n"}]}]},{"type":"element","tag":"span","props":{"class":"line","line":8},"children":[{"type":"element","tag":"span","props":{"style":"--shiki-default:#C678DD"},"children":[{"type":"text","value":"left: 0;\n"}]}]},{"type":"element","tag":"span","props":{"class":"line","line":9},"children":[{"type":"element","tag":"span","props":{"style":"--shiki-default:#C678DD"},"children":[{"type":"text","value":"right: 0;\n"}]}]},{"type":"element","tag":"span","props":{"class":"line","line":10},"children":[{"type":"element","tag":"span","props":{"emptyLinePlaceholder":true},"children":[{"type":"text","value":"\n"}]}]},{"type":"element","tag":"span","props":{"class":"line","line":11},"children":[{"type":"element","tag":"span","props":{"style":"--shiki-default:#7F848E;--shiki-default-font-style:italic"},"children":[{"type":"text","value":"/* 四邊都設，完全覆蓋父層（常見於 overlay） */\n"}]}]},{"type":"element","tag":"span","props":{"class":"line","line":12},"children":[{"type":"element","tag":"span","props":{"style":"--shiki-default:#C678DD"},"children":[{"type":"text","value":"position: absolute;\n"}]}]},{"type":"element","tag":"span","props":{"class":"line","line":13},"children":[{"type":"element","tag":"span","props":{"style":"--shiki-default:#C678DD"},"children":[{"type":"text","value":"inset: 0;\n"}]}]}]}]},{"type":"element","tag":"p","props":{},"children":[{"type":"text","value":"前提是元素"},{"type":"element","tag":"strong","props":{},"children":[{"type":"text","value":"沒有明確設定 "},{"type":"element","tag":"code","props":{"className":[]},"children":[{"type":"text","value":"width"}]},{"type":"text","value":" 或 "},{"type":"element","tag":"code","props":{"className":[]},"children":[{"type":"text","value":"height"}]}]},{"type":"text","value":"。若同時設定了固定尺寸，瀏覽器會優先尊重尺寸，拉伸不會發生。"}]},{"type":"element","tag":"p","props":{},"children":[{"type":"text","value":"以側邊欄為例，用 "},{"type":"element","tag":"code","props":{"className":[]},"children":[{"type":"text","value":"inset-y-0"}]},{"type":"text","value":"（等同 "},{"type":"element","tag":"code","props":{"className":[]},"children":[{"type":"text","value":"top: 0; bottom: 0"}]},{"type":"text","value":"）讓 "},{"type":"element","tag":"code","props":{"className":[]},"children":[{"type":"text","value":"absolute"}]},{"type":"text","value":" 定位的側邊欄撐滿父層高度："}]},{"type":"element","tag":"pre","props":{"className":"language-html shiki shiki-themes one-dark-pro","code":"<!-- 外層：提供定位基準與佔位 -->\n<div class=\"relative h-full w-24 shrink-0\">\n  <!-- 中間層：absolute 定位，inset-y-0 撐滿高度 -->\n  <div class=\"absolute inset-y-0 left-0\">\n    <!-- 內層：實際內容，hover 展開動畫 -->\n    <div class=\"h-full w-24 hover:w-50 transition-[width] duration-200\">\n      ...\n    </div>\n  </div>\n</div>\n","language":"html","meta":"","style":""},"children":[{"type":"element","tag":"code","props":{"__ignoreMap":""},"children":[{"type":"element","tag":"span","props":{"class":"line","line":1},"children":[{"type":"element","tag":"span","props":{"style":"--shiki-default:#7F848E;--shiki-default-font-style:italic"},"children":[{"type":"text","value":"<!-- 外層：提供定位基準與佔位 -->\n"}]}]},{"type":"element","tag":"span","props":{"class":"line","line":2},"children":[{"type":"element","tag":"span","props":{"style":"--shiki-default:#ABB2BF"},"children":[{"type":"text","value":"<"}]},{"type":"element","tag":"span","props":{"style":"--shiki-default:#E06C75"},"children":[{"type":"text","value":"div"}]},{"type":"element","tag":"span","props":{"style":"--shiki-default:#D19A66"},"children":[{"type":"text","value":" class"}]},{"type":"element","tag":"span","props":{"style":"--shiki-default:#ABB2BF"},"children":[{"type":"text","value":"="}]},{"type":"element","tag":"span","props":{"style":"--shiki-default:#98C379"},"children":[{"type":"text","value":"\"relative h-full w-24 shrink-0\""}]},{"type":"element","tag":"span","props":{"style":"--shiki-default:#ABB2BF"},"children":[{"type":"text","value":">\n"}]}]},{"type":"element","tag":"span","props":{"class":"line","line":3},"children":[{"type":"element","tag":"span","props":{"style":"--shiki-default:#7F848E;--shiki-default-font-style:italic"},"children":[{"type":"text","value":"  <!-- 中間層：absolute 定位，inset-y-0 撐滿高度 -->\n"}]}]},{"type":"element","tag":"span","props":{"class":"line","line":4},"children":[{"type":"element","tag":"span","props":{"style":"--shiki-default:#ABB2BF"},"children":[{"type":"text","value":"  <"}]},{"type":"element","tag":"span","props":{"style":"--shiki-default:#E06C75"},"children":[{"type":"text","value":"div"}]},{"type":"element","tag":"span","props":{"style":"--shiki-default:#D19A66"},"children":[{"type":"text","value":" class"}]},{"type":"element","tag":"span","props":{"style":"--shiki-default:#ABB2BF"},"children":[{"type":"text","value":"="}]},{"type":"element","tag":"span","props":{"style":"--shiki-default:#98C379"},"children":[{"type":"text","value":"\"absolute inset-y-0 left-0\""}]},{"type":"element","tag":"span","props":{"style":"--shiki-default:#ABB2BF"},"children":[{"type":"text","value":">\n"}]}]},{"type":"element","tag":"span","props":{"class":"line","line":5},"children":[{"type":"element","tag":"span","props":{"style":"--shiki-default:#7F848E;--shiki-default-font-style:italic"},"children":[{"type":"text","value":"    <!-- 內層：實際內容，hover 展開動畫 -->\n"}]}]},{"type":"element","tag":"span","props":{"class":"line","line":6},"children":[{"type":"element","tag":"span","props":{"style":"--shiki-default:#ABB2BF"},"children":[{"type":"text","value":"    <"}]},{"type":"element","tag":"span","props":{"style":"--shiki-default:#E06C75"},"children":[{"type":"text","value":"div"}]},{"type":"element","tag":"span","props":{"style":"--shiki-default:#D19A66"},"children":[{"type":"text","value":" class"}]},{"type":"element","tag":"span","props":{"style":"--shiki-default:#ABB2BF"},"children":[{"type":"text","value":"="}]},{"type":"element","tag":"span","props":{"style":"--shiki-default:#98C379"},"children":[{"type":"text","value":"\"h-full w-24 hover:w-50 transition-[width] duration-200\""}]},{"type":"element","tag":"span","props":{"style":"--shiki-default:#ABB2BF"},"children":[{"type":"text","value":">\n"}]}]},{"type":"element","tag":"span","props":{"class":"line","line":7},"children":[{"type":"element","tag":"span","props":{"style":"--shiki-default:#ABB2BF"},"children":[{"type":"text","value":"      ...\n"}]}]},{"type":"element","tag":"span","props":{"class":"line","line":8},"children":[{"type":"element","tag":"span","props":{"style":"--shiki-default:#ABB2BF"},"children":[{"type":"text","value":"    </"}]},{"type":"element","tag":"span","props":{"style":"--shiki-default:#E06C75"},"children":[{"type":"text","value":"div"}]},{"type":"element","tag":"span","props":{"style":"--shiki-default:#ABB2BF"},"children":[{"type":"text","value":">\n"}]}]},{"type":"element","tag":"span","props":{"class":"line","line":9},"children":[{"type":"element","tag":"span","props":{"style":"--shiki-default:#ABB2BF"},"children":[{"type":"text","value":"  </"}]},{"type":"element","tag":"span","props":{"style":"--shiki-default:#E06C75"},"children":[{"type":"text","value":"div"}]},{"type":"element","tag":"span","props":{"style":"--shiki-default:#ABB2BF"},"children":[{"type":"text","value":">\n"}]}]},{"type":"element","tag":"span","props":{"class":"line","line":10},"children":[{"type":"element","tag":"span","props":{"style":"--shiki-default:#ABB2BF"},"children":[{"type":"text","value":"</"}]},{"type":"element","tag":"span","props":{"style":"--shiki-default:#E06C75"},"children":[{"type":"text","value":"div"}]},{"type":"element","tag":"span","props":{"style":"--shiki-default:#ABB2BF"},"children":[{"type":"text","value":">\n"}]}]}]}]},{"type":"element","tag":"h2","props":{"id":"環境資訊"},"children":[{"type":"text","value":"環境資訊"}]},{"type":"element","tag":"ul","props":{},"children":[{"type":"element","tag":"li","props":{},"children":[{"type":"text","value":"Nuxt: 3.x"}]},{"type":"element","tag":"li","props":{},"children":[{"type":"text","value":"Vue: 3.x"}]},{"type":"element","tag":"li","props":{},"children":[{"type":"text","value":"UnoCSS（Tailwind-compatible utility classes）"}]}]},{"type":"element","tag":"blockquote","props":{},"children":[{"type":"element","tag":"p","props":{},"children":[{"type":"text","value":"本文撰寫時間：2026 年 3 月，技術版本可能隨時間更新，請以官方文件為準。"}]}]},{"type":"element","tag":"section","props":{"className":["footnotes"],"dataFootnotes":""},"children":[{"type":"element","tag":"h2","props":{"className":["sr-only"],"id":"footnote-label"},"children":[{"type":"text","value":"Reference"}]},{"type":"element","tag":"ol","props":{},"children":[{"type":"element","tag":"li","props":{"id":"user-content-fn-1"},"children":[{"type":"element","tag":"a","props":{"href":"https://developer.mozilla.org/en-US/docs/CSS/overflow-y","rel":["nofollow"]},"children":[{"type":"text","value":"overflow-y - CSS | MDN"}]},{"type":"text","value":" "},{"type":"element","tag":"a","props":{"href":"#user-content-fnref-1","ariaLabel":"Back to reference 1","className":["data-footnote-backref"],"dataFootnoteBackref":""},"children":[{"type":"text","value":"↩"}]}]},{"type":"element","tag":"li","props":{"id":"user-content-fn-2"},"children":[{"type":"element","tag":"a","props":{"href":"https://developer.mozilla.org/en-US/docs/Web/CSS/top/","rel":["nofollow"]},"children":[{"type":"text","value":"top - CSS | MDN"}]},{"type":"text","value":" — \"If position is set to absolute or fixed and height is unspecified, both the top and bottom values are respected.\" "},{"type":"element","tag":"a","props":{"href":"#user-content-fnref-2","ariaLabel":"Back to reference 2","className":["data-footnote-backref"],"dataFootnoteBackref":""},"children":[{"type":"text","value":"↩"}]}]}]}]},{"type":"element","tag":"style","props":{},"children":[{"type":"text","value":"html .default .shiki span {color: var(--shiki-default);background: var(--shiki-default-bg);font-style: var(--shiki-default-font-style);font-weight: var(--shiki-default-font-weight);text-decoration: var(--shiki-default-text-decoration);}html .shiki span {color: var(--shiki-default);background: var(--shiki-default-bg);font-style: var(--shiki-default-font-style);font-weight: var(--shiki-default-font-weight);text-decoration: var(--shiki-default-text-decoration);}"}]}],"toc":{"title":"","searchDepth":2,"depth":2,"links":[{"id":"問題描述","depth":2,"text":"問題描述"},{"id":"根本原因分析","depth":2,"text":"根本原因分析","children":[{"id":"h-screen-與-h-full-的差異","depth":3,"text":"h-screen 與 h-full 的差異"},{"id":"overflow-y-auto-需要明確的高度限制","depth":3,"text":"overflow-y: auto 需要明確的高度限制"}]},{"id":"修正方案","depth":2,"text":"修正方案","children":[{"id":"layout-層鎖死高度邊界","depth":3,"text":"Layout 層：鎖死高度邊界"},{"id":"page-層改用-h-full","depth":3,"text":"Page 層：改用 h-full"},{"id":"職責分工","depth":3,"text":"職責分工"}]},{"id":"延伸position-absolute-的對立方向拉伸","depth":2,"text":"延伸：position absolute 的對立方向拉伸"},{"id":"環境資訊","depth":2,"text":"環境資訊"},{"id":"footnote-label","depth":2,"text":"Reference"}]}},"_type":"markdown","_id":"content:post:20260325-nuxt3-layout-height-management.md","_source":"content","_file":"post/20260325-nuxt3-layout-height-management.md","_stem":"post/20260325-nuxt3-layout-height-management","_extension":"md","createdAt":"2026-03-25T08:00:59.000Z","updatedAt":"2026-03-25T08:00:59.000Z"}